MIPI_DPHY_Monitor/model/RX_HS_CLK_FSM.v
//==============================================================================
// RX_HS_CLK_FSM.v
// High-Speed Clock Lane FSM for MIPI D-PHY
//==============================================================================

module RX_HS_CLK_FSM #(
    parameter Tclk_miss = 10
)(
    input  clk,
    input  rst,
    input  HS_Enable,
    input  CLKDp,
    input  CLKDn,
    output reg RX_HS_CLK
);

    localparam HS_STOP = 2'b00;
    localparam HS_CLK  = 2'b01;
    localparam HS_END  = 2'b10;

    reg [1:0] hs_state, hs_next;
    integer hs_timeout;

    always @(posedge clk or posedge rst) begin
        if (rst) begin
            hs_state   <= HS_STOP;
            hs_timeout <= 0;
        end else begin
            hs_state <= hs_next;

            if (hs_state == HS_CLK) begin
                hs_timeout <= hs_timeout + 1;
            end else begin
                hs_timeout <= 0;
            end
                
        end
    end

    always @(*) begin
        hs_next = hs_state;
        RX_HS_CLK = 0;
        case (hs_state)
            HS_STOP: begin
                if (HS_Enable)
                    hs_next = HS_CLK;
            end
            HS_CLK: begin
                RX_HS_CLK = CLKDp;
                if(!HS_Enable)
                    hs_next = HS_STOP;

                else if ((hs_timeout >= Tclk_miss))
                    hs_next = HS_END;
            end
            HS_END: begin
                if(!HS_Enable)
                    hs_next = HS_STOP;
                else if (({CLKDp, CLKDn} == 2'b11))
                    hs_next = HS_STOP;
            end
        endcase
    end

endmodule

MIPI_DPHY_Monitor/model/RX_LP_CLK_FSM.v
//==============================================================================
// RX_LP_CLK_FSM.v
// Low-Power Clock Lane FSM for MIPI D-PHY
//==============================================================================

module RX_LP_CLK_FSM #(
    parameter Tclk_term_en = 2
)(
    input  clk,
    input  rst,
    input  CLKDp,
    input  CLKDn,
    output reg HS_Enable
);

    localparam RXCLK_STOP    = 2'b00;
    localparam RXCLK_HS_RQST = 2'b01;
    localparam RXCLK_HS_PRPR = 2'b10;
    localparam RXCLK_HS_TERM = 2'b11;

    reg [1:0] lp_state, lp_next;
    integer prpr_cnt;

    always @(posedge clk or posedge rst) begin
        if (rst) begin
            lp_state <= RXCLK_STOP;
            prpr_cnt <= 0;
        end else begin
            lp_state <= lp_next;
            if (lp_state == RXCLK_HS_PRPR)
                prpr_cnt <= prpr_cnt + 1;
            else
                prpr_cnt <= 0;
        end
    end

    always @(*) begin
        lp_next   = lp_state;
        HS_Enable = 1'b0;

        case (lp_state)
            RXCLK_STOP: begin
                if ({CLKDp, CLKDn} == 2'b01)
                    lp_next = RXCLK_HS_RQST;
            end

            RXCLK_HS_RQST: begin
                if({CLKDp, CLKDn} == 2'b00)
                    lp_next = RXCLK_HS_PRPR;
                else
                    lp_next = RXCLK_STOP;
            end

            RXCLK_HS_PRPR: begin
                if (prpr_cnt >= Tclk_term_en & {CLKDp,CLKDn} == 2'b00)
                    lp_next = RXCLK_HS_TERM;
            end

            RXCLK_HS_TERM: begin
                HS_Enable = 1'b1;
                if ({CLKDp, CLKDn} == 2'b11)
                    lp_next = RXCLK_STOP;
            end
        endcase
    end

endmodule

MIPI_DPHY_Monitor/model/RX_CLK_LANE.v
//==============================================================================
// RX_CLK_LANE.v
// Top module connecting LP and HS FSMs
//==============================================================================

module RX_CLK_LANE #(
    parameter Tclk_term_en = 2,
    parameter Tclk_miss    = 10
)(
    input  clk,
    input  rst,
    input  CLKDp,
    input  CLKDn,
    output RX_HS_CLK
);

    wire HS_Enable;

    RX_LP_CLK_FSM #(
        .Tclk_term_en(Tclk_term_en)
    ) lp_fsm_inst (
        .clk(clk),
        .rst(rst),
        .CLKDp(CLKDp),
        .CLKDn(CLKDn),
        .HS_Enable(HS_Enable)
    );

    RX_HS_CLK_FSM #(
        .Tclk_miss(Tclk_miss)
    ) hs_fsm_inst (
        .clk(clk),
        .rst(rst),
        .HS_Enable(HS_Enable),
        .CLKDp(CLKDp),
        .CLKDn(CLKDn),
        .RX_HS_CLK(RX_HS_CLK)
    );

endmodule

MIPI_DPHY_Monitor/sim/RX_CLK_LANE_TB.v
`timescale 1ns/1ps

module RX_CLK_LANE_TB;

    parameter Tclk_term_en = 2;
    parameter Tclk_miss    = 4;

    reg clk;
    reg rst;
    reg CLKDp;
    reg CLKDn;
    wire RX_HS_CLK;

    RX_CLK_LANE #(
        .Tclk_term_en(Tclk_term_en),
        .Tclk_miss(Tclk_miss)
    ) dut (
        .clk(clk),
        .rst(rst),
        .CLKDp(CLKDp),
        .CLKDn(CLKDn),
        .RX_HS_CLK(RX_HS_CLK)
    );


    // Clock generation: 50MHz
    initial clk = 0;
    always #10 clk = ~clk;

    initial begin
        $dumpfile("vcd/RX_CLK_LANE_TB.vcd");
        $dumpvars(0, RX_CLK_LANE_TB);
    end

    initial begin
        rst   = 1;
        CLKDp = 1;
        CLKDn = 1;

        #30 rst = 0; // Release reset


        #20 CLKDp = 0; CLKDn = 1; // 01 -> request HS
        #20 CLKDp = 0; CLKDn = 0; // 00 -> prepare HS
        # (Tclk_term_en*20) ;      // Wait for Tclk_term_en cycles
        #20 CLKDp = 1; CLKDn = 1; // back to stop


        #20 CLKDp = 0; CLKDn = 1;
        #20 CLKDp = 0; CLKDn = 0;
        repeat (Tclk_term_en) #20;
        CLKDn = ~CLKDp;
        repeat (40) begin
            #5; CLKDp = ~ CLKDp; CLKDn = ~CLKDn;
        end
        CLKDp = 1; CLKDn = 1;
        #100;


        CLKDp = 0; CLKDn = 1;
        #20 CLKDp = 0; CLKDn = 0;
        repeat (Tclk_term_en) #20;
        # (Tclk_miss*20 + 20);
        #40;
        CLKDp = 1; CLKDn = 1;


        #1000;
        $finish;
    end

endmodule

MIPI_DPHY_Monitor/vcd/RX_CLK_LANE_TB.vcd
$date
	Wed Jan 07 16:25:30 2026
$end
$version
	Icarus Verilog
$end
$timescale
	1ps
$end
$scope module RX_CLK_LANE_TB $end
$var wire 1 ! RX_HS_CLK $end
$var parameter 32 " Tclk_miss $end
$var parameter 32 # Tclk_term_en $end
$var reg 1 $ CLKDn $end
$var reg 1 % CLKDp $end
$var reg 1 & clk $end
$var reg 1 ' rst $end
$scope module dut $end
$var wire 1 $ CLKDn $end
$var wire 1 % CLKDp $end
$var wire 1 & clk $end
$var wire 1 ' rst $end
$var wire 1 ! RX_HS_CLK $end
$var wire 1 ( HS_Enable $end
$var parameter 32 ) Tclk_miss $end
$var parameter 32 * Tclk_term_en $end
$scope module hs_fsm_inst $end
$var wire 1 $ CLKDn $end
$var wire 1 % CLKDp $end
$var wire 1 & clk $end
$var wire 1 ' rst $end
$var wire 1 ( HS_Enable $end
$var parameter 2 + HS_CLK $end
$var parameter 2 , HS_END $end
$var parameter 2 - HS_STOP $end
$var parameter 32 . Tclk_miss $end
$var reg 1 ! RX_HS_CLK $end
$var reg 2 / hs_next [1:0] $end
$var reg 2 0 hs_state [1:0] $end
$var integer 32 1 hs_timeout [31:0] $end
$upscope $end
$scope module lp_fsm_inst $end
$var wire 1 $ CLKDn $end
$var wire 1 % CLKDp $end
$var wire 1 & clk $end
$var wire 1 ' rst $end
$var parameter 2 2 RXCLK_HS_PRPR $end
$var parameter 2 3 RXCLK_HS_RQST $end
$var parameter 2 4 RXCLK_HS_TERM $end
$var parameter 2 5 RXCLK_STOP $end
$var parameter 32 6 Tclk_term_en $end
$var reg 1 ( HS_Enable $end
$var reg 2 7 lp_next [1:0] $end
$var reg 2 8 lp_state [1:0] $end
$var integer 32 9 prpr_cnt [31:0] $end
$upscope $end
$upscope $end
$upscope $end
$enddefinitions $end
$comment Show the parameter values. $end
$dumpall
b10 6
b0 5
b11 4
b1 3
b10 2
b100 .
b0 -
b10 ,
b1 +
b10 *
b100 )
b10 #
b100 "
$end
#0
$dumpvars
b0 9
b0 8
b0 7
b0 1
b0 0
b0 /
0(
1'
0&
1%
1$
0!
$end
#10000
1&
#20000
0&
#30000
1&
0'
#40000
0&
#50000
b1 8
b0 7
1&
0%
#60000
0&
#70000
b10 8
b10 7
1&
0$
#80000
0&
#90000
b1 9
1&
#100000
0&
#110000
b11 7
b10 9
1&
#120000
0&
#130000
b11 9
b10 7
1&
1$
1%
#140000
0&
#150000
b100 9
1&
0%
#160000
0&
#170000
b1 /
1(
b101 9
b11 8
b11 7
1&
0$
#180000
0&
#190000
1(
b0 9
b1 0
1&
#200000
0&
#210000
b1 1
1(
1&
1$
#215000
1!
1(
0$
1%
#220000
0!
1(
1$
0%
0&
#225000
1!
1(
0$
1%
#230000
b10 1
0!
1(
1$
0%
1&
#235000
1!
1(
0$
1%
#240000
0!
1(
1$
0%
0&
#245000
1!
1(
0$
1%
#250000
b11 1
0!
1(
1$
0%
1&
#255000
1!
1(
0$
1%
#260000
0!
1(
1$
0%
0&
#265000
1!
1(
0$
1%
#270000
b10 /
b100 1
0!
1(
1$
0%
1&
#275000
1!
b10 /
1(
0$
1%
#280000
0!
b10 /
1(
1$
0%
0&
#285000
1!
b10 /
1(
0$
1%
#290000
b101 1
b10 0
0!
b10 /
1(
1$
0%
1&
#295000
1(
0$
1%
#300000
1(
1$
0%
0&
#305000
1(
0$
1%
#310000
b0 1
1(
1$
0%
1&
#315000
1(
0$
1%
#320000
1(
1$
0%
0&
#325000
1(
0$
1%
#330000
1(
1$
0%
1&
#335000
1(
0$
1%
#340000
1(
1$
0%
0&
#345000
1(
0$
1%
#350000
1(
1$
0%
1&
#355000
1(
0$
1%
#360000
1(
1$
0%
0&
#365000
1(
0$
1%
#370000
1(
1$
0%
1&
#375000
1(
0$
1%
#380000
1(
1$
0%
0&
#385000
1(
0$
1%
#390000
1(
1$
0%
1&
#395000
1(
0$
1%
#400000
1(
1$
0%
0&
#405000
1(
0$
1%
#410000
b0 /
b0 7
1(
1$
1%
1&
#420000
0&
#430000
0(
b0 /
b0 8
b0 0
1&
#440000
0&
#450000
1&
#460000
0&
#470000
1&
#480000
0&
#490000
1&
#500000
0&
#510000
b1 8
b0 7
1&
0%
#520000
0&
#530000
b10 8
b10 7
1&
0$
#540000
0&
#550000
b1 9
1&
#560000
0&
#570000
b11 7
b10 9
1&
#580000
0&
#590000
b1 /
1(
b11 9
b11 8
1&
#600000
0&
#610000
1(
b1 0
b0 9
1&
#620000
0&
#630000
b1 1
1&
#640000
0&
#650000
b10 1
1&
#660000
0&
#670000
b11 1
1&
#680000
0&
#690000
b10 /
b100 1
1&
#700000
0&
#710000
b0 8
b101 1
b10 0
0!
b0 /
b0 7
0(
1&
1$
1%
#720000
0&
#730000
b0 1
b0 0
1&
