MIPI_DPHY_Driver/rtl/DEFF.v
//==============================================================================
//  Module      : DEFF
//  Description :
//  DDR Output Flip-Flop block for MIPI D-PHY TX datapath.
//  Samples serial data on both rising and falling edges of the TX DDR clock
//  and drives a differential DDR output.
//
//  Designer    : NH
//  Company     : ITI
//
//  Notes       :
//  - Serial_B1 is sampled on the rising edge of TX_DDR_clk
//  - Serial_B2 is sampled on the falling edge of TX_DDR_clk
//  - Outputs are tri-stated when Enable is deasserted
//==============================================================================

module DEFF (
    // Clock and Reset
    input  wire TX_DDR_clk,   // DDR transmit clock
    input  wire TX_rst,       // Asynchronous reset (active high)

    // Control
    input  wire Enable,       // Output enable

    // DDR Data Inputs
    input  wire Serial_B1,    // Rising-edge data
    input  wire Serial_B2,    // Falling-edge data

    // Differential Outputs
    output wire Dp,           // Positive output
    output wire Dn            // Negative output
);

    // Internal DDR registers
    reg q1;   // Rising-edge register
    reg q2;   // Falling-edge register

    // Rising-edge sampling
    always @(posedge TX_DDR_clk or posedge TX_rst) begin
        if (TX_rst)
            q1 <= 1'b0;
        else if (Enable)
            q1 <= Serial_B1;
    end

    // Falling-edge sampling
    always @(negedge TX_DDR_clk or posedge TX_rst) begin
        if (TX_rst)
            q2 <= 1'b0;
        else if (Enable)
            q2 <= Serial_B2;
    end

    // Glitch-free DDR output using XOR
    wire ddr_out;

    assign ddr_out = (q1 & TX_DDR_clk) ^ (q2 & ~TX_DDR_clk);

    // Differential outputs
    assign Dp = Enable ? ddr_out : 1'bz;
    assign Dn = Enable ? ~ddr_out : 1'bz;

endmodule

MIPI_DPHY_Driver/sim/DEFF_TB.v
`timescale 1ns/1ps
//==============================================================================
//  Testbench   : DEFF_TB
//  Description :
//  Functional testbench for the DEFF DDR output flip-flop.
//  Verifies rising-edge and falling-edge data sampling, enable control,
//  reset behavior, and differential output operation.
//
//  Designer    : NH
//  Company     : ITI
//==============================================================================

module DEFF_TB;

    //-------------------------------------------------------------------------
    // DUT Interface Signals
    //-------------------------------------------------------------------------
    reg  TX_DDR_clk;
    reg  TX_rst;
    reg  Enable;
    reg  Serial_B1;
    reg  Serial_B2;

    wire Dp;
    wire Dn;

    //-------------------------------------------------------------------------
    // DUT Instantiation
    //-------------------------------------------------------------------------
    DEFF dut (
        .TX_DDR_clk (TX_DDR_clk),
        .TX_rst     (TX_rst),
        .Enable     (Enable),
        .Serial_B1  (Serial_B1),
        .Serial_B2  (Serial_B2),
        .Dp         (Dp),
        .Dn         (Dn)
    );

    //-------------------------------------------------------------------------
    // DDR Clock Generation (100 MHz)
    //-------------------------------------------------------------------------
    initial begin
        TX_DDR_clk = 1'b0;
        forever #5 TX_DDR_clk = ~TX_DDR_clk;
    end

    //-------------------------------------------------------------------------
    // Stimulus Process
    //-------------------------------------------------------------------------
    initial begin
        // Initial conditions
        TX_rst    = 1'b1;
        Enable    = 1'b0;
        Serial_B1 = 1'b0;
        Serial_B2 = 1'b0;

        // Apply reset
        #20;
        TX_rst = 1'b0;

        // Enable DDR operation
        #22;
        Enable = 1'b1;

        // Drive DDR data
        repeat (4) begin
            Serial_B1 = $random % 2;
            Serial_B2 = $random % 2;
            #10;
        end

        // Disable outputs
        #20;
        Enable = 1'b0;

        // Input changes while disabled
        #10;
        Serial_B1 = 1'b1;
        Serial_B2 = 1'b1;

        // Re-enable DDR operation
        #10;
        Enable = 1'b1;

        // End simulation
        #30;
        $finish;
    end

    initial begin
        $dumpfile("vcd/DEFF_TB.vcd");
        $dumpvars(0, DEFF_TB);
    end

endmodule

MIPI_DPHY_Driver/vcd/DEFF_TB.vcd
$date
	Wed Jan 07 11:53:34 2026
$end
$version
	Icarus Verilog
$end
$timescale
	1ps
$end
$scope module DEFF_TB $end
$var wire 1 ! Dp $end
$var wire 1 " Dn $end
$var reg 1 # Enable $end
$var reg 1 $ Serial_B1 $end
$var reg 1 % Serial_B2 $end
$var reg 1 & TX_DDR_clk $end
$var reg 1 ' TX_rst $end
$scope module dut $end
$var wire 1 # Enable $end
$var wire 1 $ Serial_B1 $end
$var wire 1 % Serial_B2 $end
$var wire 1 & TX_DDR_clk $end
$var wire 1 ' TX_rst $end
$var wire 1 ( ddr_out $end
$var wire 1 ! Dp $end
$var wire 1 " Dn $end
$var reg 1 ) q1 $end
$var reg 1 * q2 $end
$upscope $end
$upscope $end
$enddefinitions $end
$comment Show the parameter values. $end
$dumpall
$end
#0
$dumpvars
0*
0)
0(
1'
0&
0%
0$
0#
z"
z!
$end
#5000
1&
#10000
0&
#15000
1&
#20000
0&
0'
#25000
1&
#30000
0&
#35000
1&
#40000
0&
#42000
0!
1"
1%
1#
#45000
1&
#50000
0"
1!
1(
1*
0&
#52000
1$
#55000
1)
0"
1!
1(
1&
#60000
0&
#65000
1&
#70000
0&
#72000
0%
#75000
1&
#80000
1"
0!
0(
0*
0&
#85000
0"
1!
1(
1&
#90000
1"
0!
0(
0&
#95000
0"
1!
1(
1&
#100000
1"
0!
0(
0&
#102000
z!
z"
0#
#105000
1(
1&
#110000
0(
0&
#112000
1%
#115000
1(
1&
#120000
0(
0&
#122000
0!
1"
1#
#125000
0"
1!
1(
1&
#130000
1*
0"
1!
1(
0&
